lokalise_mcp/__init__.py
lokalise_mcp/__main__.py
lokalise_mcp/config.py
lokalise_mcp/git_utils.py
lokalise_mcp/key_extractor.py
lokalise_mcp/lokalise_client.py
lokalise_mcp/safety.py
lokalise_mcp/server.py
lokalise_mcp/translator.py
lokalise_mcp-0.2.0.dist-info/METADATA
lokalise_mcp-0.2.0.dist-info/WHEEL
lokalise_mcp-0.2.0.dist-info/entry_points.txt
lokalise_mcp-0.2.0.dist-info/licenses/LICENSE
lokalise_mcp-0.2.0.dist-info/RECORD
