Metadata-Version: 2.4
Name: lokalise-mcp
Version: 0.2.0
Summary: MCP server for syncing translation keys to Lokalise with AI-powered translations
Project-URL: Homepage, https://github.com/yourusername/lokalise-mcp
Project-URL: Documentation, https://github.com/yourusername/lokalise-mcp#readme
Project-URL: Repository, https://github.com/yourusername/lokalise-mcp
Project-URL: Issues, https://github.com/yourusername/lokalise-mcp/issues
Author-email: Sijan <sijan@example.com>
License: MIT
License-File: LICENSE
Keywords: ai,claude,i18n,localization,lokalise,mcp,translation
Classifier: Development Status :: 4 - Beta
Classifier: Intended Audience :: Developers
Classifier: License :: OSI Approved :: MIT License
Classifier: Programming Language :: Python :: 3
Classifier: Programming Language :: Python :: 3.10
Classifier: Programming Language :: Python :: 3.11
Classifier: Programming Language :: Python :: 3.12
Classifier: Topic :: Software Development :: Internationalization
Classifier: Topic :: Software Development :: Localization
Requires-Python: >=3.10
Requires-Dist: anthropic>=0.39.0
Requires-Dist: fastmcp>=2.0.0
Requires-Dist: gitpython>=3.1.43
Requires-Dist: python-dotenv>=1.0.0
Requires-Dist: python-lokalise-api>=3.0.0
Provides-Extra: dev
Requires-Dist: black>=24.0.0; extra == 'dev'
Requires-Dist: pytest-asyncio>=0.23.0; extra == 'dev'
Requires-Dist: pytest>=8.0.0; extra == 'dev'
Requires-Dist: ruff>=0.1.0; extra == 'dev'
